README.txt
setup.py
collective/__init__.py
collective.recipe.isapiwsgi.egg-info/PKG-INFO
collective.recipe.isapiwsgi.egg-info/SOURCES.txt
collective.recipe.isapiwsgi.egg-info/dependency_links.txt
collective.recipe.isapiwsgi.egg-info/entry_points.txt
collective.recipe.isapiwsgi.egg-info/namespace_packages.txt
collective.recipe.isapiwsgi.egg-info/requires.txt
collective.recipe.isapiwsgi.egg-info/top_level.txt
collective.recipe.isapiwsgi.egg-info/zip-safe
collective/recipe/__init__.py
collective/recipe/isapiwsgi/__init__.py
docs/HISTORY.txt