Metadata-Version: 1.0
Name: collective.recipe.isapiwsgi
Version: 1.0b1
Summary: ISAPI-WSGI wrapper based on buildout configuration
Home-page: UNKNOWN
Author: Martin Aspeli
Author-email: optilude@gmail.com
License: ZPL
Platform: UNKNOWN
Classifier: Framework :: Buildout
Classifier: Intended Audience :: Developers
Classifier: Intended Audience :: System Administrators
Classifier: License :: OSI Approved :: Zope Public License
Classifier: Programming Language :: Python
